molfunc_ext.cpython-39-darwin.so
molfunc/__init__.py
molfunc/fragments.py
molfunc/molecules.py
molfunc/molfunc.py
molfunc/molfunc_ext.pyx
molfunc/include/angles.h
molfunc/include/atoms.h
molfunc/include/graph.h
molfunc/include/grid.h
molfunc/include/rotation.h
molfunc/include/utils.h
molfunc/include/vector3d.h
molfunc/include/species/combined.h
molfunc/include/species/fragments.h
molfunc/include/species/molecules.h
molfunc/include/species/species.h
molfunc/scripts/compile_fragments.py
molfunc/src/angles.cpp
molfunc/src/atoms.cpp
molfunc/src/graph.cpp
molfunc/src/grid.cpp
molfunc/src/rotation.cpp
molfunc/src/utils.cpp
molfunc/src/vector3d.cpp
molfunc/src/species/combined.cpp
molfunc/src/species/fragments.cpp
molfunc/src/species/molecules.cpp
molfunc/src/species/species.cpp
molfunc-2.0.0b0.dist-info/LICENSE.md
molfunc-2.0.0b0.dist-info/METADATA
molfunc-2.0.0b0.dist-info/WHEEL
molfunc-2.0.0b0.dist-info/entry_points.txt
molfunc-2.0.0b0.dist-info/top_level.txt
molfunc-2.0.0b0.dist-info/RECORD
