Metadata-Version: 2.1
Name: molfunc
Version: 2.0.0b0
Summary: Fast molecular functionalisation
Home-page: https://github.com/duartegroup/molfunc
Author: Tom Young
Author-email: tom.young@chem.ox.ac.uk
License: MIT
Platform: any
License-File: LICENSE.md
